Workbook

Sheet 3-way by class
A1: September 2026 - three-way reconciliation of sales volume (MWh)
A2: Earnings Sheet (finance) vs Power BI (Monthly Sales report, customer billed = 1) vs Sales Platform (jps_actuals). Differences are formulas.
A4: Class | B4: Earnings Sheet | C4: Power BI (billed = 1) | D4: Sales Platform | E4: Sheet - Power BI | F4: Power BI - Platform | G4: Sheet - Platform
A5: RT10 | B5: 114073.57 | C5: 114565.97 | D5: 114565.97 | E5: =B5-C5 | F5: =C5-D5 | G5: =B5-D5
A6: RT20 | B6: 61067.922 | C6: 60617.571 | D6: 60617.571 | E6: =B6-C6 | F6: =C6-D6 | G6: =B6-D6
A7: RT40 | B7: 67272.954 | C7: 67312.956 | D7: 67312.952 | E7: =B7-C7 | F7: =C7-D7 | G7: =B7-D7
A8: RT50 | B8: 30252.674 | C8: 30252.675 | D8: 30252.675 | E8: =B8-C8 | F8: =C8-D8 | G8: =B8-D8
A9: RT60-ST | B9: 3414.8725 | C9: 3413.1935 | D9: 3413.193 | E9: =B9-C9 | F9: =C9-D9 | G9: =B9-D9
A10: RT70 | B10: 18642.652 | C10: 18642.652 | D10: 18642.652 | E10: =B10-C10 | F10: =C10-D10 | G10: =B10-D10
A11: Total | B11: =SUM(B5:B10) | C11: =SUM(C5:C10) | D11: =SUM(D5:D10) | E11: =SUM(E5:E10) | F11: =SUM(F5:F10) | G11: =SUM(G5:G10)
A13: Notes
A14: Power BI and the Platform agree to within 0.01 MWh in every class: the Platform is the Power BI customer-billed = 1 line.
A15: Earnings Sheet vs the other two: (1) the Sheet includes not-billed rows (RT10 -11.5, RT20 -30.5, RT60 street lighting +1.7 MWh); (2) RT40 is 40.0 MWh lower on the Sheet, same raw file, cause not identified; (3) the Sheet puts "unassigned"-tariff prepaid (589.7 MWh) in RT20 and everything else in RT10, whereas Power BI and the Platform put only RT20-PAYG (108.9 MWh) in RT20 - this moves 480.9 MWh RT10 -> RT20 with no effect on the total (inferred: ties to the third decimal).
A16: Power BI has 9.0 MWh of prepaid with a blank rate category; it is included in RT10 above, as the Platform books it.
A17: Power BI customer-billed = 0 rows (not in any report): EV tariff +68.9 MWh and credits/adjustments -40.4 MWh, net +28.6 MWh. Power BI grand total incl. these is 294,833.6 MWh - see the Bridge sheet.

Sheet Bridge
A1: Bridge: Earnings Sheet -> Power BI (billed = 1) -> Sales Platform (MWh, September 2026 total)
A3: Step | B3: MWh | C3: Running total | D3: Comment
A4: Earnings Sheet total | B4: ='3-way by class'!B11 | C4: =B4 | D4: Sheet total MWh (RT10..RT70)
A5: + Remove not-billed rows carried on the Sheet | B5: =-SUM('Transactions - not billed'!I5:I82)/1000 | C5: =C4+B5 | D5: 78 transactions on the "Transactions - not billed" sheet (RT10 -11.5, RT20 -30.5, RT60 street lighting +1.7)
A6: + RT40 difference | B6: 40.00169 | C6: =C5+B6 | D6: Same raw file, Sheet RT40 lower by this amount - transaction NOT identified, see "RT40 gap" sheet
A7: =Power BI billed = 1 (computed) | C7: =C6
A8: Power BI billed = 1 (reported) | B8: ='3-way by class'!C11 | D8: Power BI pivot, customer billed = 1 line (postpaid + prepaid), Sep-2026
A9: Unreconciled (computed - reported) | C9: =C7-B8 | D9: Rounding in the Sheet class figures
A10: Platform less Power BI billed = 1 | B10: ='3-way by class'!D11-'3-way by class'!C11 | C10: =C8+B10 | D10: Rounding (whole-kWh account rows)
A11: =Sales Platform total | C11: =C10
A12: Sales Platform total (jps_actuals) | B12: ='3-way by class'!D11 | D12: Queried from jps_actuals
A13: Unreconciled (computed - platform) | C13: =C11-B12 | D13: Should be 0
A15: Memo - Power BI grand total (all rows) | B15: =B8+B16+B17 | D15: What the Power BI pivot shows as Grand Total
A16: + EV tariff (customer billed = 0) | B16: 68.93917 | D16: In no report
A17: + not-billed credits/adjustments | B17: -40.36384 | D17: In no report except the Sheet

Sheet Components
A1: What each source includes (MWh). Values from the Power BI table (Sep-2026); Y/N = included in that report.
A3: Component | B3: Class | C3: MWh | D3: Earnings Sheet | E3: Power BI (billed = 1) | F3: Sales Platform | G3: Note
A4: Postpaid billed - RT10 (RM+EM) | B4: RT10 | C4: 111556.15 | D4: Y | E4: Y | F4: Y
A5: Prepaid-tagged billed (PR10) | B5: RT10 | C5: 113.08744 | D5: Y | E5: Y | F5: Y | G5: In the postpaid file; premise also in the prepaid report. Includes one 99.99 MWh bill (cust 1598805)
A6: Prepaid report - RT10-PAYG tariff | B6: RT10 | C6: 2298.0175 | D6: Y | E6: Y | F6: Y
A7: Prepaid report - unassigned tariff | B7: RT10 (Sheet: RT20) | C7: 589.73089 | D7: Y | E7: Y | F7: Y | G7: Class differs: Sheet shows it in RT20
A8: Prepaid report - blank tariff | B8: RT10 | C8: 8.984244 | D8: Y | E8: Y | F8: Y | G8: Blank rate category in Power BI
A9: Postpaid billed - RT20 (CM) | B9: RT20 | C9: 60508.686 | D9: Y | E9: Y | F9: Y
A10: Prepaid-tagged billed (PC / PR20) | B10: RT20 | C10: 0.02675 | D10: Y | E10: Y | F10: Y
A11: Prepaid report - RT20-PAYG tariff | B11: RT20 (Sheet: RT10) | C11: 108.85756 | D11: Y | E11: Y | F11: Y | G11: Class differs: Sheet shows it in RT10
A12: RT40 billed (LC-40) | B12: RT40 | C12: 67312.956 | D12: Y (less 40.0) | E12: Y | F12: Y | G12: Sheet RT40 is 40.002 MWh lower - unexplained
A13: RT50 billed (LC-50) | B13: RT50 | C13: 30252.675 | D13: Y | E13: Y | F13: Y
A14: RT60 billed (ST+TL) | B14: RT60-ST | C14: 3413.1935 | D14: Y | E14: Y | F14: Y
A15: RT70 billed (WT) | B15: RT70 | C15: 18642.652 | D15: Y | E15: Y | F15: Y
A16: Not-billed rows - RT10 (RM+EM+PR) | B16: RT10 | C16: -11.52279 | D16: Y | E16: N | F16: N | G16: Credits/adjustments flagged cust_billed = 0
A17: Not-billed rows - RT20 (CM+PC) | B17: RT20 | C17: -30.52005 | D17: Y | E17: N | F17: N
A18: Not-billed rows - RT60 (ST) | B18: RT60-ST | C18: 1.679 | D18: Y | E18: N | F18: N
A19: EV tariff (26 premises) - not billed | B19: EV | C19: 68.93917 | D19: N | E19: N | F19: N | G19: Flagged cust_billed = 0; in no report
A20: Total of components included in Power BI (billed = 1) | C20: =SUMIF(E4:E19,"Y",C4:C19)
A21: Power BI billed = 1 total (check) | C21: ='3-way by class'!C11
A22: Difference | C22: =C20-C21
A23: All components (= Power BI grand total) | C23: =SUM(C4:C19)

Sheet Revenue (indicative)
A1: Revenue by class, J$ - indicative only, the sources are NOT on the same basis
A3: Class | B3: Earnings Sheet | C3: Power BI billed = 1 (postpaid net_revenue; model has no prepaid revenue) | D3: Sales Platform (net of GCT) | E3: Sheet - Platform
A4: RT10 | B4: 6.6326806e+09 | C4: 6.4583926e+09 | D4: 6.6249777e+09 | E4: =B4-D4
A5: RT20 | B5: 3.291304e+09 | C5: 3.2929174e+09 | D5: 3.2994864e+09 | E5: =B5-D5
A6: RT40 | B6: 3.2469272e+09 | C6: 3.1998385e+09 | D6: 3199838484 | E6: =B6-D6
A7: RT50 | B7: 1.2096111e+09 | C7: 1.2030806e+09 | D7: 1203080583 | E7: =B7-D7
A8: RT60-ST | B8: 2.136971e+08 | C8: 2.136971e+08 | D8: 213697099 | E8: =B8-D8
A9: RT70 | B9: 8.0052775e+08 | C9: 8.7414347e+08 | D9: 874143463 | E9: =B9-D9
A10: Total | B10: =SUM(B4:B9) | C10: =SUM(C4:C9) | D10: =SUM(D4:D9) | E10: =SUM(E4:E9)
A12: The Sheet revenue includes items the other two do not carry (fuel exchange, rate adjustments, true-ups, RPD interest). Power BI has no prepaid revenue. Not bridged.

Sheet Transactions - not billed
A1: Not-billed transactions the Earnings Sheet carries in RT10 / RT20 / RT60 (cust_billed = 0, kWh <> 0), September 2026 raw billing file
A2: Power BI (billed = 1) and the Platform exclude these. Total kWh feeds the Bridge sheet.
A4: Cust code | B4: Premise | C4: Name | D4: Srat code | E4: Rate class | F4: Class | G4: Parish | H4: Account status | I4: kWh | J4: Net revenue J$
A5: 1433340 | B5: 593842 | C5: Bryan, Alfred D. | D5: RT10 | E5: RM | F5: RT10 | G5: Spanish Town | H5: I | I5: -1948.33 | J5: -110344.91
A6: 503497 | B6: 507968 | C6: Bee, John M. | D6: RT10 | E6: RM | F6: RT10 | G6: St. Ann's Bay | H6: I | I6: -1305.25 | J6: -77741.4
A7: 1435209 | B7: 984929 | C7: Atland, Monique M. | D7: RT10 | E7: RM | F7: RT10 | G7: Montego Bay | H7: I | I7: -1022.54 | J7: -68671.33
A8: 1591991 | B8: 1039010 | C8: Nelson, Melissa L. | D8: RT10 | E8: RM | F8: RT10 | G8: Spanish Town | H8: I | I8: -851.6 | J8: -51816.63
A9: 435172 | B9: 437728 | C9: Cooke, Ezron | D9: RT10 | E9: RM | F9: RT10 | G9: Montego Bay | H9: I | I9: -845.5 | J9: -46917.46
A10: 297436 | B10: 299443 | C10: Ingram, Rupert | D10: RT10 | E10: RM | F10: RT10 | G10: KSA South | H10: I | I10: -621.36 | J10: -34761.97
A11: 629944 | B11: 866428 | C11: Heron, Merle | D11: RT10 | E11: RM | F11: RT10 | G11: Sav-la-Mar | H11: I | I11: -588.39 | J11: -33975.44
A12: 1582452 | B12: 1228882 | C12: Nettleford, Ingrid F. | D12: RT10 | E12: RM | F12: RT10 | G12: Montego Bay | H12: I | I12: -522.97 | J12: -30713.56
A13: 152818 | B13: 154383 | C13: Ledgister, Trevor A. | D13: RT10 | E13: RM | F13: RT10 | G13: Black River | H13: I | I13: -491.51 | J13: -29196.42
A14: 1053289 | B14: 176925 | C14: Beckford, Damean L. | D14: RT10 | E14: RM | F14: RT10 | G14: Portmore | H14: I | I14: -466.02 | J14: -27206.19
A15: 1590418 | B15: 680177 | C15: Gooden, Tianna A. | D15: RT10 | E15: RM | F15: RT10 | G15: Spanish Town | H15: I | I15: -450.17 | J15: -23896.57
A16: 1299149 | B16: 1159895 | C16: Sheyer, Elfie J. | D16: RT10 | E16: RM | F16: RT10 | G16: Black River | H16: I | I16: -408.34 | J16: -28527.65
... A82: 101175 | B82: 102181 | C82: St. Mary Parish Council | D82: H400 | E82: ST | F82: RT60-ST | G82: Port Maria | H82: A | I82: 176 | J82: 0
C84: Total | I84: =SUM(I5:I82) | J84: =SUM(J5:J82)
C85: RT10 | I85: =SUMIF(F5:F82,"RT10",I5:I82) | J85: =SUMIF(F5:F82,"RT10",J5:J82)
C86: RT20 | I86: =SUMIF(F5:F82,"RT20",I5:I82) | J86: =SUMIF(F5:F82,"RT20",J5:J82)
C87: RT60-ST | I87: =SUMIF(F5:F82,"RT60-ST",I5:I82) | J87: =SUMIF(F5:F82,"RT60-ST",J5:J82)

Sheet RT40 gap
A1: RT40: Earnings Sheet vs raw billing file (same September 2026 billing data)
A3: Item | B3: Value | C3: Unit
A4: Raw file, RT40 (LC-40) billed rows | B4: 1963 | C4: count
A5: Raw file, distinct RT40 premises (billed) | B5: 1962 | C5: count
A6: Earnings Sheet, RT40 customers | B6: 1962 | C6: count
A7: Raw file RT40 kWh | B7: 67312956 | C7: kWh
A8: Earnings Sheet RT40 kWh | B8: 67272954 | C8: kWh
A9: Gap (raw - Sheet) | B9: 40001.69 | C9: kWh
A11: What this shows
A12: The Sheet customer count (1,962) equals the number of distinct RT40 premises in the raw file, so no whole account is missing from the Sheet: the gap is a kWh difference on accounts that are counted.
A13: No single RT40 bill equals the gap. The only round-number bill near it is Salada Foods Jamaica Ltd, 40,000.00 kWh, J$2,019,806 (cust 100826, premise 101454), about 2 kWh from the gap. Candidate only, not confirmed.
A14: 20 pairs of RT40 bills also sum to the gap within +/-0.6 kWh, so matching on the amount alone cannot identify the transaction. The billing run or the finance adjustment listing is needed to confirm.
A16: Candidate transactions
A17: Name / premise | B17: kWh | C17: Net revenue J$
A18: Salada Foods Jamaica Ltd (100826-101454) - single bill | B18: 40000 | C18: 2019806.2
A19: Sweet Craft Limited (688747-730784) + Salada Foods Jamaica Ltd (100826-101454) - two bills | B19: 40002.04 | C19: 2204088.9
A20: Needle, Alice (909657-794215) + Kingston Wharves Ltd (100912-101573) - two bills | B20: 40001.6 | C20: 1857320.7
A21: Bank of Nova Scotia (100073-142820) + National Water Commission (100012-604911) - two bills | B21: 40001.2 | C21: 2066070.1
