Workbook

Sheet How to read
A1: Non-fuel revenue walk, September 2026
A2: Non-fuel revenue = Energy line (energy + demand + F/X) + Customer charge, from the finance Revenues sheet. The walk explains the variance in five pieces:
A3: Customer charge: the fixed monthly charge per customer. It moves with the number of customers, not with kWh.
A4: Volume: total normalized sales (MWh) above or below the comparison, valued at the comparison average rate. Only the change in how much was sold.
A5: Mix: the shift of those MWh between rate classes. Classes earn different amounts per kWh (RT10 earns the most, RT50 the least), so selling relatively more RT10 raises the average even if nothing is repriced. It is between-class.
A6: FX: the change in US$ revenue from J$ billing at a different exchange rate. Estimated from the billing FX rates, scaled to the share of revenue finance shows as FX-exposed (their YTD FX bar of US$89K).
A7: Other yield: what is left of the per-kWh change after FX. It is within-class: customers moving up the residential consumption blocks, demand (kVA) billing, indexation and billing/accrual timing. There has been no base-rate increase; this is not a price change.
A8: Sheets: Inputs holds every source number (blue). Each comparison sheet is formulas only, so clicking a cell shows how it was built. The yellow check cells must read 0.
A9: Class detail is allocated: the financials have no class split of normalized sales or non-fuel revenue, so billed class data is scaled to the finance totals (Step 2). Class mix and other yield are therefore estimates; the totals tie to finance.

Sheet Inputs
A1: Inputs - every number used in the walk (blue cells are source values)
A3: 1. Finance (JPSCo Financials 09-26, Revenues sheet)
A4: Item | B4: Sept actual | C4: Sept budget | D4: Sept prior year | E4: YTD actual | F4: YTD budget | G4: YTD prior year | H4: Source
A5: Energy line (US$000) | B5: 27977 | C5: 26935.181 | D5: 27451 | E5: 231376 | F5: 224730.66 | G5: 237631 | H5: Revenues row 13; columns: month actual C, budget F, prior year W; YTD actual L, budget M, prior YTD T
A6: Customer charge (US$000) | B6: 3339 | C6: 3198.289 | D6: 3229 | E6: 29442 | F6: 29012.606 | G6: 29207 | H6: Revenues row 14; columns: month actual C, budget F, prior year W; YTD actual L, budget M, prior YTD T
A7: Sales, normalized (MWh) | B7: 300193.78 | C7: 303681.99 | D7: 297076 | E7: 2471820.2 | F7: 2427355.1 | G7: 2568506.3 | H7: Revenues row 46; columns: month actual C, budget F, prior year W; YTD actual L, budget M, prior YTD T
A8: Billing FX rate (J$/US$) | B8: 159.0239 | C8: 160.86811 | D8: 161.0926 | E8: 158.52774 | F8: 158.88422 | G8: 159.09264 | H8: Revenues row 32; columns: month actual C, budget F, prior year W; YTD actual L, budget M, prior YTD T
A9: Finance FX effect, YTD vs budget (US$000) | E9: 89 | H9: Corporate Performance Report slide 11 (Non-Fuel Revenue Variance Analysis, FX bar)
A11: 2. Class detail from billed data (used only for the class shares)
A12: MWh and energy+demand revenue (J$000). Sept actual = Earnings Sheet; YTD actual = platform Jan-Aug + Earnings Sheet Sept; prior year = platform (customer billed = 1); budget = budget file with the F/X adjustment lines allocated pro rata. Customer charge is carried separately on the finance line.
A13: Class | B13: Sept actual MWh | C13: Sept actual energy+demand J$000 | D13: Sept budget MWh | E13: Sept budget energy+demand J$000 | F13: Sept prior year MWh | G13: Sept prior year energy+demand J$000 | H13: YTD actual MWh | I13: YTD actual energy+demand J$000 | J13: YTD budget MWh | K13: YTD budget energy+demand J$000 | L13: YTD prior year MWh | M13: YTD prior year energy+demand J$000
A14: RT10 | B14: 114073.57 | C14: 1964340.7 | D14: 104830 | E14: 1674438.9 | F14: 110279.24 | G14: 1864816.7 | H14: 882108.99 | I14: 14556669 | J14: 852217 | K14: 13552017 | L14: 909697.75 | M14: 14943401
A15: RT20 | B15: 61067.922 | C15: 617453.54 | D15: 57649 | E15: 607752.9 | F15: 58277.527 | G15: 594417.3 | H15: 476211.72 | I15: 4852266.2 | J15: 459863 | K15: 4827036.5 | L15: 490520.91 | M15: 5000878.7
A16: RT40 | B16: 67272.954 | C16: 1142457.5 | D16: 73334 | E16: 1202868.4 | F16: 68941.054 | G16: 1122372.5 | H16: 569726.82 | I16: 9540174.1 | J16: 594517 | K16: 10329799 | L16: 605323.82 | M16: 9948801.8
A17: RT50 | B17: 30252.674 | C17: 345202.26 | D17: 35268 | E17: 417262.15 | F17: 33527.203 | G17: 370576.37 | H17: 259548.8 | I17: 3085993 | J17: 276034 | K17: 3512562.8 | L17: 287170.24 | M17: 3359089.5
A18: RT60-ST | B18: 3414.8725 | C18: 48052.654 | D18: 3312 | E18: 47976.344 | F18: 3408.535 | G18: 47982.203 | H18: 27492.13 | I18: 387106.82 | J18: 28174 | K18: 406353.86 | L18: 30381.836 | M18: 427730.12
A19: RT70 | B19: 18642.652 | C19: 271066.87 | D19: 22866 | E19: 349129.27 | F19: 27281.357 | G19: 347983.28 | H19: 213868.49 | I19: 2951672.1 | J19: 191229 | K19: 3051448.2 | L19: 226863.02 | M19: 3150881.3

Sheet Sep vs budget
A1: September 2026 vs budget - non-fuel revenue walk
A2: US$'000 unless stated. Every cell below is a formula on the Inputs sheet.
A4: Step 1 - finance totals
B5: Actual | C5: Comparison | D5: Variance | E5: Var %
A6: Energy line (energy + demand + F/X) | B6: =Inputs!$B$5 | C6: =Inputs!$C$5 | D6: =B6-C6 | E6: =D6/C6
A7: Customer charge | B7: =Inputs!$B$6 | C7: =Inputs!$C$6 | D7: =B7-C7 | E7: =D7/C7
A8: Sales, normalized (MWh) | B8: =Inputs!$B$7 | C8: =Inputs!$C$7 | D8: =B8-C8 | E8: =D8/C8
A9: Billing FX rate (J$/US$) | B9: =Inputs!$B$8 | C9: =Inputs!$C$8 | D9: =B9-C9 | E9: =D9/C9
A10: Non-fuel revenue (energy line + customer charge) | B10: =B6+B7 | C10: =C6+C7 | D10: =B10-C10 | E10: =D10/C10
A12: Step 2 - scale the class data to the finance totals
A13: Volume factor, actual = finance MWh / sum of billed class MWh | B13: =B8/SUM(Inputs!$B$14:$B$19)
A14: Volume factor, comparison | B14: =C8/SUM(Inputs!$D$14:$D$19)
A15: Revenue factor, actual = finance energy line / sum of class energy+demand | B15: =B6/(SUM(Inputs!$C$14:$C$19)/1)
A16: Revenue factor, comparison | B16: =C6/(SUM(Inputs!$E$14:$E$19)/1)
A18: Step 3 - volume, mix and rate on the energy line, by class
A19: Class | B19: Comparison MWh | C19: Actual MWh | D19: Comparison US$000 | E19: Actual US$000 | F19: Comparison US cents/kWh | G19: Actual US cents/kWh | H19: Volume | I19: Mix | J19: Rate | K19: Total
A20: RT10 | B20: =Inputs!$D$14*$B$14 | C20: =Inputs!$B$14*$B$13 | D20: =Inputs!$E$14*$B$16 | E20: =Inputs!$C$14*$B$15 | F20: =D20/B20*100 | G20: =E20/C20*100 | H20: =(C$26*B20/B$26-B20)*(D20/B20) | I20: =(C20-C$26*B20/B$26)*(D20/B20) | J20: =E20-C20*(D20/B20) | K20: =SUM(H20:J20)
A21: RT20 | B21: =Inputs!$D$15*$B$14 | C21: =Inputs!$B$15*$B$13 | D21: =Inputs!$E$15*$B$16 | E21: =Inputs!$C$15*$B$15 | F21: =D21/B21*100 | G21: =E21/C21*100 | H21: =(C$26*B21/B$26-B21)*(D21/B21) | I21: =(C21-C$26*B21/B$26)*(D21/B21) | J21: =E21-C21*(D21/B21) | K21: =SUM(H21:J21)
A22: RT40 | B22: =Inputs!$D$16*$B$14 | C22: =Inputs!$B$16*$B$13 | D22: =Inputs!$E$16*$B$16 | E22: =Inputs!$C$16*$B$15 | F22: =D22/B22*100 | G22: =E22/C22*100 | H22: =(C$26*B22/B$26-B22)*(D22/B22) | I22: =(C22-C$26*B22/B$26)*(D22/B22) | J22: =E22-C22*(D22/B22) | K22: =SUM(H22:J22)
A23: RT50 | B23: =Inputs!$D$17*$B$14 | C23: =Inputs!$B$17*$B$13 | D23: =Inputs!$E$17*$B$16 | E23: =Inputs!$C$17*$B$15 | F23: =D23/B23*100 | G23: =E23/C23*100 | H23: =(C$26*B23/B$26-B23)*(D23/B23) | I23: =(C23-C$26*B23/B$26)*(D23/B23) | J23: =E23-C23*(D23/B23) | K23: =SUM(H23:J23)
A24: RT60-ST | B24: =Inputs!$D$18*$B$14 | C24: =Inputs!$B$18*$B$13 | D24: =Inputs!$E$18*$B$16 | E24: =Inputs!$C$18*$B$15 | F24: =D24/B24*100 | G24: =E24/C24*100 | H24: =(C$26*B24/B$26-B24)*(D24/B24) | I24: =(C24-C$26*B24/B$26)*(D24/B24) | J24: =E24-C24*(D24/B24) | K24: =SUM(H24:J24)
A25: RT70 | B25: =Inputs!$D$19*$B$14 | C25: =Inputs!$B$19*$B$13 | D25: =Inputs!$E$19*$B$16 | E25: =Inputs!$C$19*$B$15 | F25: =D25/B25*100 | G25: =E25/C25*100 | H25: =(C$26*B25/B$26-B25)*(D25/B25) | I25: =(C25-C$26*B25/B$26)*(D25/B25) | J25: =E25-C25*(D25/B25) | K25: =SUM(H25:J25)
A26: Total | B26: =SUM(B20:B25) | C26: =SUM(C20:C25) | D26: =SUM(D20:D25) | E26: =SUM(E20:E25) | F26: =D26/B26*100 | G26: =E26/C26*100 | H26: =SUM(H20:H25) | I26: =SUM(I20:I25) | J26: =SUM(J20:J25) | K26: =SUM(K20:K25)
A27: Check: energy-line variance - (volume + mix + rate) | K27: =D6-K26
A29: Step 4 - take FX out of rate
A30: FX if all revenue were J$-denominated (upper bound) = actual energy line x (comparison FX / actual FX - 1) | B30: =B6*(C9/B9-1)
A31: Share of revenue actually exposed to FX = finance YTD FX effect / YTD upper bound | B31: =Inputs!$E$9/(Inputs!$E$5*(Inputs!$F$8/Inputs!$E$8-1))
A32: FX effect used (upper bound x exposed share) | B32: =B30*B31
A33: Other yield = rate - FX | B33: =J26-B32
A35: Step 5 - the walk
A36: Customer charge (fixed charge per customer, finance line) | B36: =D7
A37: Energy line - volume | B37: =H26
A38: Energy line - mix between classes | B38: =I26
A39: Energy line - FX | B39: =B32
A40: Energy line - other yield (within-class) | B40: =B33
A41: Non-fuel revenue variance | B41: =SUM(B36:B40)
A42: Check against finance (B10 variance) | B42: =D10-B41

Sheet Sep vs prior year
A1: September 2026 vs September 2025 - non-fuel revenue walk
A2: US$'000 unless stated. Every cell below is a formula on the Inputs sheet.
A4: Step 1 - finance totals
B5: Actual | C5: Comparison | D5: Variance | E5: Var %
A6: Energy line (energy + demand + F/X) | B6: =Inputs!$B$5 | C6: =Inputs!$D$5 | D6: =B6-C6 | E6: =D6/C6
A7: Customer charge | B7: =Inputs!$B$6 | C7: =Inputs!$D$6 | D7: =B7-C7 | E7: =D7/C7
A8: Sales, normalized (MWh) | B8: =Inputs!$B$7 | C8: =Inputs!$D$7 | D8: =B8-C8 | E8: =D8/C8
A9: Billing FX rate (J$/US$) | B9: =Inputs!$B$8 | C9: =Inputs!$D$8 | D9: =B9-C9 | E9: =D9/C9
A10: Non-fuel revenue (energy line + customer charge) | B10: =B6+B7 | C10: =C6+C7 | D10: =B10-C10 | E10: =D10/C10
A12: Step 2 - scale the class data to the finance totals
A13: Volume factor, actual = finance MWh / sum of billed class MWh | B13: =B8/SUM(Inputs!$B$14:$B$19)
A14: Volume factor, comparison | B14: =C8/SUM(Inputs!$F$14:$F$19)
A15: Revenue factor, actual = finance energy line / sum of class energy+demand | B15: =B6/(SUM(Inputs!$C$14:$C$19)/1)
A16: Revenue factor, comparison | B16: =C6/(SUM(Inputs!$G$14:$G$19)/1)
A18: Step 3 - volume, mix and rate on the energy line, by class
A19: Class | B19: Comparison MWh | C19: Actual MWh | D19: Comparison US$000 | E19: Actual US$000 | F19: Comparison US cents/kWh | G19: Actual US cents/kWh | H19: Volume | I19: Mix | J19: Rate | K19: Total
A20: RT10 | B20: =Inputs!$F$14*$B$14 | C20: =Inputs!$B$14*$B$13 | D20: =Inputs!$G$14*$B$16 | E20: =Inputs!$C$14*$B$15 | F20: =D20/B20*100 | G20: =E20/C20*100 | H20: =(C$26*B20/B$26-B20)*(D20/B20) | I20: =(C20-C$26*B20/B$26)*(D20/B20) | J20: =E20-C20*(D20/B20) | K20: =SUM(H20:J20)
A21: RT20 | B21: =Inputs!$F$15*$B$14 | C21: =Inputs!$B$15*$B$13 | D21: =Inputs!$G$15*$B$16 | E21: =Inputs!$C$15*$B$15 | F21: =D21/B21*100 | G21: =E21/C21*100 | H21: =(C$26*B21/B$26-B21)*(D21/B21) | I21: =(C21-C$26*B21/B$26)*(D21/B21) | J21: =E21-C21*(D21/B21) | K21: =SUM(H21:J21)
A22: RT40 | B22: =Inputs!$F$16*$B$14 | C22: =Inputs!$B$16*$B$13 | D22: =Inputs!$G$16*$B$16 | E22: =Inputs!$C$16*$B$15 | F22: =D22/B22*100 | G22: =E22/C22*100 | H22: =(C$26*B22/B$26-B22)*(D22/B22) | I22: =(C22-C$26*B22/B$26)*(D22/B22) | J22: =E22-C22*(D22/B22) | K22: =SUM(H22:J22)
A23: RT50 | B23: =Inputs!$F$17*$B$14 | C23: =Inputs!$B$17*$B$13 | D23: =Inputs!$G$17*$B$16 | E23: =Inputs!$C$17*$B$15 | F23: =D23/B23*100 | G23: =E23/C23*100 | H23: =(C$26*B23/B$26-B23)*(D23/B23) | I23: =(C23-C$26*B23/B$26)*(D23/B23) | J23: =E23-C23*(D23/B23) | K23: =SUM(H23:J23)
A24: RT60-ST | B24: =Inputs!$F$18*$B$14 | C24: =Inputs!$B$18*$B$13 | D24: =Inputs!$G$18*$B$16 | E24: =Inputs!$C$18*$B$15 | F24: =D24/B24*100 | G24: =E24/C24*100 | H24: =(C$26*B24/B$26-B24)*(D24/B24) | I24: =(C24-C$26*B24/B$26)*(D24/B24) | J24: =E24-C24*(D24/B24) | K24: =SUM(H24:J24)
A25: RT70 | B25: =Inputs!$F$19*$B$14 | C25: =Inputs!$B$19*$B$13 | D25: =Inputs!$G$19*$B$16 | E25: =Inputs!$C$19*$B$15 | F25: =D25/B25*100 | G25: =E25/C25*100 | H25: =(C$26*B25/B$26-B25)*(D25/B25) | I25: =(C25-C$26*B25/B$26)*(D25/B25) | J25: =E25-C25*(D25/B25) | K25: =SUM(H25:J25)
A26: Total | B26: =SUM(B20:B25) | C26: =SUM(C20:C25) | D26: =SUM(D20:D25) | E26: =SUM(E20:E25) | F26: =D26/B26*100 | G26: =E26/C26*100 | H26: =SUM(H20:H25) | I26: =SUM(I20:I25) | J26: =SUM(J20:J25) | K26: =SUM(K20:K25)
A27: Check: energy-line variance - (volume + mix + rate) | K27: =D6-K26
A29: Step 4 - take FX out of rate
A30: FX if all revenue were J$-denominated (upper bound) = actual energy line x (comparison FX / actual FX - 1) | B30: =B6*(C9/B9-1)
A31: Share of revenue actually exposed to FX = finance YTD FX effect / YTD upper bound | B31: =Inputs!$E$9/(Inputs!$E$5*(Inputs!$F$8/Inputs!$E$8-1))
A32: FX effect used (upper bound x exposed share) | B32: =B30*B31
A33: Other yield = rate - FX | B33: =J26-B32
A35: Step 5 - the walk
A36: Customer charge (fixed charge per customer, finance line) | B36: =D7
A37: Energy line - volume | B37: =H26
A38: Energy line - mix between classes | B38: =I26
A39: Energy line - FX | B39: =B32
A40: Energy line - other yield (within-class) | B40: =B33
A41: Non-fuel revenue variance | B41: =SUM(B36:B40)
A42: Check against finance (B10 variance) | B42: =D10-B41

Sheet YTD vs budget
A1: January-September 2026 vs budget - non-fuel revenue walk
A2: US$'000 unless stated. Every cell below is a formula on the Inputs sheet.
A4: Step 1 - finance totals
B5: Actual | C5: Comparison | D5: Variance | E5: Var %
A6: Energy line (energy + demand + F/X) | B6: =Inputs!$E$5 | C6: =Inputs!$F$5 | D6: =B6-C6 | E6: =D6/C6
A7: Customer charge | B7: =Inputs!$E$6 | C7: =Inputs!$F$6 | D7: =B7-C7 | E7: =D7/C7
A8: Sales, normalized (MWh) | B8: =Inputs!$E$7 | C8: =Inputs!$F$7 | D8: =B8-C8 | E8: =D8/C8
A9: Billing FX rate (J$/US$) | B9: =Inputs!$E$8 | C9: =Inputs!$F$8 | D9: =B9-C9 | E9: =D9/C9
A10: Non-fuel revenue (energy line + customer charge) | B10: =B6+B7 | C10: =C6+C7 | D10: =B10-C10 | E10: =D10/C10
A12: Step 2 - scale the class data to the finance totals
A13: Volume factor, actual = finance MWh / sum of billed class MWh | B13: =B8/SUM(Inputs!$H$14:$H$19)
A14: Volume factor, comparison | B14: =C8/SUM(Inputs!$J$14:$J$19)
A15: Revenue factor, actual = finance energy line / sum of class energy+demand | B15: =B6/(SUM(Inputs!$I$14:$I$19)/1)
A16: Revenue factor, comparison | B16: =C6/(SUM(Inputs!$K$14:$K$19)/1)
A18: Step 3 - volume, mix and rate on the energy line, by class
A19: Class | B19: Comparison MWh | C19: Actual MWh | D19: Comparison US$000 | E19: Actual US$000 | F19: Comparison US cents/kWh | G19: Actual US cents/kWh | H19: Volume | I19: Mix | J19: Rate | K19: Total
A20: RT10 | B20: =Inputs!$J$14*$B$14 | C20: =Inputs!$H$14*$B$13 | D20: =Inputs!$K$14*$B$16 | E20: =Inputs!$I$14*$B$15 | F20: =D20/B20*100 | G20: =E20/C20*100 | H20: =(C$26*B20/B$26-B20)*(D20/B20) | I20: =(C20-C$26*B20/B$26)*(D20/B20) | J20: =E20-C20*(D20/B20) | K20: =SUM(H20:J20)
A21: RT20 | B21: =Inputs!$J$15*$B$14 | C21: =Inputs!$H$15*$B$13 | D21: =Inputs!$K$15*$B$16 | E21: =Inputs!$I$15*$B$15 | F21: =D21/B21*100 | G21: =E21/C21*100 | H21: =(C$26*B21/B$26-B21)*(D21/B21) | I21: =(C21-C$26*B21/B$26)*(D21/B21) | J21: =E21-C21*(D21/B21) | K21: =SUM(H21:J21)
A22: RT40 | B22: =Inputs!$J$16*$B$14 | C22: =Inputs!$H$16*$B$13 | D22: =Inputs!$K$16*$B$16 | E22: =Inputs!$I$16*$B$15 | F22: =D22/B22*100 | G22: =E22/C22*100 | H22: =(C$26*B22/B$26-B22)*(D22/B22) | I22: =(C22-C$26*B22/B$26)*(D22/B22) | J22: =E22-C22*(D22/B22) | K22: =SUM(H22:J22)
A23: RT50 | B23: =Inputs!$J$17*$B$14 | C23: =Inputs!$H$17*$B$13 | D23: =Inputs!$K$17*$B$16 | E23: =Inputs!$I$17*$B$15 | F23: =D23/B23*100 | G23: =E23/C23*100 | H23: =(C$26*B23/B$26-B23)*(D23/B23) | I23: =(C23-C$26*B23/B$26)*(D23/B23) | J23: =E23-C23*(D23/B23) | K23: =SUM(H23:J23)
A24: RT60-ST | B24: =Inputs!$J$18*$B$14 | C24: =Inputs!$H$18*$B$13 | D24: =Inputs!$K$18*$B$16 | E24: =Inputs!$I$18*$B$15 | F24: =D24/B24*100 | G24: =E24/C24*100 | H24: =(C$26*B24/B$26-B24)*(D24/B24) | I24: =(C24-C$26*B24/B$26)*(D24/B24) | J24: =E24-C24*(D24/B24) | K24: =SUM(H24:J24)
A25: RT70 | B25: =Inputs!$J$19*$B$14 | C25: =Inputs!$H$19*$B$13 | D25: =Inputs!$K$19*$B$16 | E25: =Inputs!$I$19*$B$15 | F25: =D25/B25*100 | G25: =E25/C25*100 | H25: =(C$26*B25/B$26-B25)*(D25/B25) | I25: =(C25-C$26*B25/B$26)*(D25/B25) | J25: =E25-C25*(D25/B25) | K25: =SUM(H25:J25)
A26: Total | B26: =SUM(B20:B25) | C26: =SUM(C20:C25) | D26: =SUM(D20:D25) | E26: =SUM(E20:E25) | F26: =D26/B26*100 | G26: =E26/C26*100 | H26: =SUM(H20:H25) | I26: =SUM(I20:I25) | J26: =SUM(J20:J25) | K26: =SUM(K20:K25)
A27: Check: energy-line variance - (volume + mix + rate) | K27: =D6-K26
A29: Step 4 - take FX out of rate
A30: FX if all revenue were J$-denominated (upper bound) = actual energy line x (comparison FX / actual FX - 1) | B30: =B6*(C9/B9-1)
A31: Share of revenue actually exposed to FX = finance YTD FX effect / YTD upper bound | B31: =Inputs!$E$9/(Inputs!$E$5*(Inputs!$F$8/Inputs!$E$8-1))
A32: FX effect used (upper bound x exposed share) | B32: =B30*B31
A33: Other yield = rate - FX | B33: =J26-B32
A35: Step 5 - the walk
A36: Customer charge (fixed charge per customer, finance line) | B36: =D7
A37: Energy line - volume | B37: =H26
A38: Energy line - mix between classes | B38: =I26
A39: Energy line - FX | B39: =B32
A40: Energy line - other yield (within-class) | B40: =B33
A41: Non-fuel revenue variance | B41: =SUM(B36:B40)
A42: Check against finance (B10 variance) | B42: =D10-B41

Sheet YTD vs prior year
A1: January-September 2026 vs prior year - non-fuel revenue walk
A2: US$'000 unless stated. Every cell below is a formula on the Inputs sheet.
A4: Step 1 - finance totals
B5: Actual | C5: Comparison | D5: Variance | E5: Var %
A6: Energy line (energy + demand + F/X) | B6: =Inputs!$E$5 | C6: =Inputs!$G$5 | D6: =B6-C6 | E6: =D6/C6
A7: Customer charge | B7: =Inputs!$E$6 | C7: =Inputs!$G$6 | D7: =B7-C7 | E7: =D7/C7
A8: Sales, normalized (MWh) | B8: =Inputs!$E$7 | C8: =Inputs!$G$7 | D8: =B8-C8 | E8: =D8/C8
A9: Billing FX rate (J$/US$) | B9: =Inputs!$E$8 | C9: =Inputs!$G$8 | D9: =B9-C9 | E9: =D9/C9
A10: Non-fuel revenue (energy line + customer charge) | B10: =B6+B7 | C10: =C6+C7 | D10: =B10-C10 | E10: =D10/C10
A12: Step 2 - scale the class data to the finance totals
A13: Volume factor, actual = finance MWh / sum of billed class MWh | B13: =B8/SUM(Inputs!$H$14:$H$19)
A14: Volume factor, comparison | B14: =C8/SUM(Inputs!$L$14:$L$19)
A15: Revenue factor, actual = finance energy line / sum of class energy+demand | B15: =B6/(SUM(Inputs!$I$14:$I$19)/1)
A16: Revenue factor, comparison | B16: =C6/(SUM(Inputs!$M$14:$M$19)/1)
A18: Step 3 - volume, mix and rate on the energy line, by class
A19: Class | B19: Comparison MWh | C19: Actual MWh | D19: Comparison US$000 | E19: Actual US$000 | F19: Comparison US cents/kWh | G19: Actual US cents/kWh | H19: Volume | I19: Mix | J19: Rate | K19: Total
A20: RT10 | B20: =Inputs!$L$14*$B$14 | C20: =Inputs!$H$14*$B$13 | D20: =Inputs!$M$14*$B$16 | E20: =Inputs!$I$14*$B$15 | F20: =D20/B20*100 | G20: =E20/C20*100 | H20: =(C$26*B20/B$26-B20)*(D20/B20) | I20: =(C20-C$26*B20/B$26)*(D20/B20) | J20: =E20-C20*(D20/B20) | K20: =SUM(H20:J20)
A21: RT20 | B21: =Inputs!$L$15*$B$14 | C21: =Inputs!$H$15*$B$13 | D21: =Inputs!$M$15*$B$16 | E21: =Inputs!$I$15*$B$15 | F21: =D21/B21*100 | G21: =E21/C21*100 | H21: =(C$26*B21/B$26-B21)*(D21/B21) | I21: =(C21-C$26*B21/B$26)*(D21/B21) | J21: =E21-C21*(D21/B21) | K21: =SUM(H21:J21)
A22: RT40 | B22: =Inputs!$L$16*$B$14 | C22: =Inputs!$H$16*$B$13 | D22: =Inputs!$M$16*$B$16 | E22: =Inputs!$I$16*$B$15 | F22: =D22/B22*100 | G22: =E22/C22*100 | H22: =(C$26*B22/B$26-B22)*(D22/B22) | I22: =(C22-C$26*B22/B$26)*(D22/B22) | J22: =E22-C22*(D22/B22) | K22: =SUM(H22:J22)
A23: RT50 | B23: =Inputs!$L$17*$B$14 | C23: =Inputs!$H$17*$B$13 | D23: =Inputs!$M$17*$B$16 | E23: =Inputs!$I$17*$B$15 | F23: =D23/B23*100 | G23: =E23/C23*100 | H23: =(C$26*B23/B$26-B23)*(D23/B23) | I23: =(C23-C$26*B23/B$26)*(D23/B23) | J23: =E23-C23*(D23/B23) | K23: =SUM(H23:J23)
A24: RT60-ST | B24: =Inputs!$L$18*$B$14 | C24: =Inputs!$H$18*$B$13 | D24: =Inputs!$M$18*$B$16 | E24: =Inputs!$I$18*$B$15 | F24: =D24/B24*100 | G24: =E24/C24*100 | H24: =(C$26*B24/B$26-B24)*(D24/B24) | I24: =(C24-C$26*B24/B$26)*(D24/B24) | J24: =E24-C24*(D24/B24) | K24: =SUM(H24:J24)
A25: RT70 | B25: =Inputs!$L$19*$B$14 | C25: =Inputs!$H$19*$B$13 | D25: =Inputs!$M$19*$B$16 | E25: =Inputs!$I$19*$B$15 | F25: =D25/B25*100 | G25: =E25/C25*100 | H25: =(C$26*B25/B$26-B25)*(D25/B25) | I25: =(C25-C$26*B25/B$26)*(D25/B25) | J25: =E25-C25*(D25/B25) | K25: =SUM(H25:J25)
A26: Total | B26: =SUM(B20:B25) | C26: =SUM(C20:C25) | D26: =SUM(D20:D25) | E26: =SUM(E20:E25) | F26: =D26/B26*100 | G26: =E26/C26*100 | H26: =SUM(H20:H25) | I26: =SUM(I20:I25) | J26: =SUM(J20:J25) | K26: =SUM(K20:K25)
A27: Check: energy-line variance - (volume + mix + rate) | K27: =D6-K26
A29: Step 4 - take FX out of rate
A30: FX if all revenue were J$-denominated (upper bound) = actual energy line x (comparison FX / actual FX - 1) | B30: =B6*(C9/B9-1)
A31: Share of revenue actually exposed to FX = finance YTD FX effect / YTD upper bound | B31: =Inputs!$E$9/(Inputs!$E$5*(Inputs!$F$8/Inputs!$E$8-1))
A32: FX effect used (upper bound x exposed share) | B32: =B30*B31
A33: Other yield = rate - FX | B33: =J26-B32
A35: Step 5 - the walk
A36: Customer charge (fixed charge per customer, finance line) | B36: =D7
A37: Energy line - volume | B37: =H26
A38: Energy line - mix between classes | B38: =I26
A39: Energy line - FX | B39: =B32
A40: Energy line - other yield (within-class) | B40: =B33
A41: Non-fuel revenue variance | B41: =SUM(B36:B40)
A42: Check against finance (B10 variance) | B42: =D10-B41
